pysqlar/__init__.py
pysqlar/archive.py
test/__init__.py
test/test_archive.py
pysqlar-0.1.3.dist-info/LICENSE
pysqlar-0.1.3.dist-info/METADATA
pysqlar-0.1.3.dist-info/WHEEL
pysqlar-0.1.3.dist-info/top_level.txt
pysqlar-0.1.3.dist-info/RECORD
