Metadata-Version: 2.1
Name: pysqlar
Version: 0.1.3
Summary: Pure Python library for working with SQLite Archives.
Home-page: http://github.com/Frojdholm/pysqlar
Author: Hampus Fröjdholm
Author-email: hampus.frojdholm@gmail.com
License: MIT
Classifier: License :: OSI Approved :: MIT License
Classifier: Programming Language :: Python :: 3
Requires-Python: >=3
License-File: LICENSE
